geteddytor_django/__init__.py
geteddytor_django/prepare.py
geteddytor_django/widgets.py
geteddytor_django/__pycache__/__init__.cpython-312.pyc
geteddytor_django/__pycache__/fields.py
geteddytor_django/__pycache__/widgets.cpython-312.pyc
geteddytor_django/static/eddytor/eddytor.umd.js
geteddytor_django/templates/eddytor/widget.html
geteddytor_django-0.18.2.dist-info/licenses/LICENSE
geteddytor_django-0.18.2.dist-info/METADATA
geteddytor_django-0.18.2.dist-info/WHEEL
geteddytor_django-0.18.2.dist-info/top_level.txt
geteddytor_django-0.18.2.dist-info/RECORD
