Metadata-Version: 2.4
Name: geteddytor_django
Version: 0.18.2
Summary: Buzzerboy's getEddyTor WSYISYG Editor is a django plugin that allows us to have dynamic use editing of rich text content
Home-page: 
Author: Buzzerboy
Author-email: Buzzerboy Inc <info@buzzerboy.com>
Project-URL: Homepage, https://www.buzzerboy.com/
Project-URL: Issues, https://dev.azure.com/buzzerboyinc/buzzerboy
Classifier: Programming Language :: Python :: 3
Classifier: License :: OSI Approved :: MIT License
Classifier: Operating System :: OS Independent
Requires-Python: >=3.8
License-File: LICENSE
Dynamic: author
Dynamic: license-file
